tatort_schedule/__init__.py
tatort_schedule/schedule.py
tatort_schedule-0.3.2.dist-info/LICENSE
tatort_schedule-0.3.2.dist-info/METADATA
tatort_schedule-0.3.2.dist-info/WHEEL
tatort_schedule-0.3.2.dist-info/top_level.txt
tatort_schedule-0.3.2.dist-info/RECORD
