Metadata-Version: 2.1
Name: tatort-schedule
Version: 0.3.2
Home-page: https://github.com/Tanikai/tatort-schedule
Author: Tanikai
Author-email: kai.anter@web.de
Project-URL: Bug Tracker, https://github.com/Tanikai/tatort-schedule/issues
Classifier: Programming Language :: Python :: 3
Classifier: License :: OSI Approved :: GNU General Public License v3 (GPLv3)
Classifier: Operating System :: OS Independent
Requires-Python: >=3.0
License-File: LICENSE
Requires-Dist: beautifulsoup4
Requires-Dist: python-dateutil
